ZtjFastApiRoute.py
ZtjFastApiServe.py
fastapi_tools-0.0.3.dist-info/METADATA
fastapi_tools-0.0.3.dist-info/WHEEL
fastapi_tools-0.0.3.dist-info/top_level.txt
fastapi_tools-0.0.3.dist-info/RECORD
