Metadata-Version: 2.1
Name: fastapi-tools
Version: 0.0.3
Summary: fastapi tools
Home-page: https://github.com/ztj1993/py-fastapi-tools
Author: ZhangTianJie
Author-email: ztj1993@gmail.com
License: MIT License
Keywords: fastapi
Platform: UNKNOWN
Requires-Dist: uvicorn
Requires-Dist: fastapi
Requires-Dist: get-port
Requires-Dist: dir-import (==0.0.3)
